cstag_cli/__init__.py
cstag_cli/append/__init__.py
cstag_cli/append/appender.py
cstag_cli/main.py
cstag_cli/utils/__init__.py
cstag_cli/utils/io.py
cstag_cli-1.0.0.dist-info/LICENSE
cstag_cli-1.0.0.dist-info/METADATA
cstag_cli-1.0.0.dist-info/WHEEL
cstag_cli-1.0.0.dist-info/entry_points.txt
cstag_cli-1.0.0.dist-info/RECORD
