Metadata-Version: 2.1
Name: cstag-cli
Version: 1.0.0
Summary: Command line interface of cstag to manipulate the minimap2's CS tag
Home-page: https://github.com/akikuno/cstag-cli
License: MIT
Author: Akihiro Kuno
Author-email: akuno@md.tsukuba.ac.jp
Requires-Python: >=3.7,<4.0
Classifier: Intended Audience :: Science/Research
Classifier: License :: OSI Approved :: MIT License
Classifier: Operating System :: MacOS
Classifier: Operating System :: POSIX
Classifier: Operating System :: Unix
Classifier: Programming Language :: Python :: 3
Classifier: Programming Language :: Python :: 3.7
Classifier: Programming Language :: Python :: 3.8
Classifier: Programming Language :: Python :: 3.9
Classifier: Programming Language :: Python :: 3.10
Classifier: Programming Language :: Python :: 3.11
Classifier: Topic :: Scientific/Engineering :: Bio-Informatics
Requires-Dist: cstag (>=0.6.2)
Requires-Dist: pysam (>=0.19.0)
Project-URL: Repository, https://github.com/akikuno/cstag-cli
